fractopo/__init__.py
fractopo/__main__.py
fractopo/analysis/__init__.py
fractopo/analysis/anisotropy.py
fractopo/analysis/azimuth.py
fractopo/analysis/contour_grid.py
fractopo/analysis/length_distributions.py
fractopo/analysis/line_data.py
fractopo/analysis/multi_network.py
fractopo/analysis/network.py
fractopo/analysis/parameters.py
fractopo/analysis/random_sampling.py
fractopo/analysis/relationships.py
fractopo/analysis/subsampling.py
fractopo/branches_and_nodes.py
fractopo/cli.py
fractopo/fractopo_utils.py
fractopo/general.py
fractopo/tval/__init__.py
fractopo/tval/proximal_traces.py
fractopo/tval/trace_validation.py
fractopo/tval/trace_validation_utils.py
fractopo/tval/trace_validators.py
fractopo-0.8.0.dist-info/LICENSE.md
fractopo-0.8.0.dist-info/METADATA
fractopo-0.8.0.dist-info/WHEEL
fractopo-0.8.0.dist-info/entry_points.txt
fractopo-0.8.0.dist-info/RECORD
