Metadata-Version: 2.3
Name: fractopo
Version: 0.8.0
Summary: Fracture Network Analysis
Home-page: https://github.com/nialov/fractopo
License: MIT
Keywords: data,gis,geology,fracture,topology
Author: nialov
Author-email: nikolasovaskainen@gmail.com
Requires-Python: >=3.9,<3.13
Classifier: Development Status :: 4 - Beta
Classifier: Intended Audience :: Science/Research
Classifier: Topic :: Scientific/Engineering :: GIS
Classifier: License :: OSI Approved :: MIT License
Classifier: Programming Language :: Python :: 3 :: Only
Provides-Extra: dev
Requires-Dist: beartype (>=0.19.0)
Requires-Dist: click
Requires-Dist: codespell (>=2.2.2) ; extra == "dev"
Requires-Dist: cogapp (>=3.3.0) ; extra == "dev"
Requires-Dist: coverage (>=6.5.0) ; extra == "dev"
Requires-Dist: geopandas (>=1.0.0)
Requires-Dist: hypothesis ; extra == "dev"
Requires-Dist: ipython ; extra == "dev"
Requires-Dist: joblib (>=1.2.0)
Requires-Dist: json5 ; extra == "dev"
Requires-Dist: jupyterlab ; extra == "dev"
Requires-Dist: marimo ; extra == "dev"
Requires-Dist: matplotlib (>=3.5.3)
Requires-Dist: nbstripout (>=0.6.1) ; extra == "dev"
Requires-Dist: numpy (>=1.26.0,<3.0.0)
Requires-Dist: pandas (>=2.1.0,<3.0.0)
Requires-Dist: powerlaw
Requires-Dist: pre-commit ; extra == "dev"
Requires-Dist: pyinstrument ; extra == "dev"
Requires-Dist: pyproj (>=3.6.0)
Requires-Dist: pytest ; extra == "dev"
Requires-Dist: pytest-regressions (>=2.2.0,<3.0.0) ; extra == "dev"
Requires-Dist: python-ternary
Requires-Dist: rich (>=11.0.0)
Requires-Dist: scikit-learn
Requires-Dist: scipy (>=1.9.1)
Requires-Dist: seaborn
Requires-Dist: shapely (>=2.0.0,<3.0.0)
Requires-Dist: toml ; extra == "dev"
Requires-Dist: typer (>=0.4)
Project-URL: Documentation, https://nialov.github.io/fractopo/
Project-URL: Repository, https://github.com/nialov/fractopo
